pandoc_mermaid_filter.py
pandoc_unsafe_mermaid_filter-0.1.0.dist-info/LICENSE
pandoc_unsafe_mermaid_filter-0.1.0.dist-info/METADATA
pandoc_unsafe_mermaid_filter-0.1.0.dist-info/WHEEL
pandoc_unsafe_mermaid_filter-0.1.0.dist-info/entry_points.txt
pandoc_unsafe_mermaid_filter-0.1.0.dist-info/top_level.txt
pandoc_unsafe_mermaid_filter-0.1.0.dist-info/RECORD
